honest_anchor/__init__.py
honest_anchor/cli.py
honest_anchor-0.1.2.dist-info/licenses/LICENSE
tests/__init__.py
tests/test_cli.py
honest_anchor-0.1.2.dist-info/METADATA
honest_anchor-0.1.2.dist-info/WHEEL
honest_anchor-0.1.2.dist-info/entry_points.txt
honest_anchor-0.1.2.dist-info/top_level.txt
honest_anchor-0.1.2.dist-info/RECORD
