Metadata-Version: 2.4
Name: honest-anchor
Version: 0.1.2
Summary: git commit for your IP - Timestamp your files to Bitcoin
Author-email: Stellanium Ltd <admin@stellanium.io>
License: MIT
Project-URL: Homepage, https://github.com/stellanium/honest-anchor
Project-URL: Documentation, https://anchor.stellanium.io
Project-URL: Repository, https://github.com/stellanium/honest-anchor
Keywords: bitcoin,timestamp,ip,protection,prior-art,opentimestamps
Classifier: Development Status :: 3 - Alpha
Classifier: Environment :: Console
Classifier: Intended Audience :: Developers
Classifier: License :: Other/Proprietary License
Classifier: Operating System :: OS Independent
Classifier: Programming Language :: Python :: 3
Classifier: Programming Language :: Python :: 3.8
Classifier: Programming Language :: Python :: 3.9
Classifier: Programming Language :: Python :: 3.10
Classifier: Programming Language :: Python :: 3.11
Classifier: Programming Language :: Python :: 3.12
Classifier: Topic :: Security :: Cryptography
Classifier: Topic :: Software Development :: Version Control
Requires-Python: >=3.8
License-File: LICENSE
Requires-Dist: click>=8.0.0
Requires-Dist: rich>=13.0.0
Requires-Dist: opentimestamps-client>=0.7.0
Requires-Dist: pyyaml>=6.0
Dynamic: license-file
